random_port/__init__.py
random_port/pool.py
random_port/py.typed
random_port-0.0.8.dist-info/licenses/LICENSE.txt
random_port-0.0.8.dist-info/METADATA
random_port-0.0.8.dist-info/WHEEL
random_port-0.0.8.dist-info/top_level.txt
random_port-0.0.8.dist-info/RECORD
