Metadata-Version: 2.4
Name: random-port
Version: 0.0.8
Summary: Generate a free TCP or UDP random port
Author-email: Fabrício Barros Cabral <fabriciofx@gmail.com>
License-Expression: MIT
Project-URL: homepage, https://github.com/fabriciofx/random-port
Project-URL: bug-tracker, https://github.com/fabriciofx/random-port/issues
Keywords: socket,tcp,udp,random,port,test
Requires-Python: >=3.14
License-File: LICENSE.txt
Dynamic: license-file
